{
  "indexes": [
    {
      "collectionGroup": "commerceSubcategories",
      "queryScope": "COLLECTION",
      "fields": [
        {
          "fieldPath": "categoryId",
          "order": "ASCENDING"
        },
        {
          "fieldPath": "orderIndex",
          "order": "ASCENDING"
        }
      ]
    },
    {
      "collectionGroup": "commerceProducts",
      "queryScope": "COLLECTION",
      "fields": [
        {
          "fieldPath": "categoryId",
          "order": "ASCENDING"
        },
        {
          "fieldPath": "subcategoryId",
          "order": "ASCENDING"
        },
        {
          "fieldPath": "orderIndex",
          "order": "ASCENDING"
        }
      ]
    },
    {
      "collectionGroup": "commerceProducts",
      "queryScope": "COLLECTION",
      "fields": [
        {
          "fieldPath": "subcategoryId",
          "order": "ASCENDING"
        },
        {
          "fieldPath": "orderIndex",
          "order": "ASCENDING"
        }
      ]
    },
    {
      "collectionGroup": "commerceProducts",
      "queryScope": "COLLECTION",
      "fields": [
        {
          "fieldPath": "visible",
          "order": "ASCENDING"
        },
        {
          "fieldPath": "categoryId",
          "order": "ASCENDING"
        },
        {
          "fieldPath": "subcategoryId",
          "order": "ASCENDING"
        },
        {
          "fieldPath": "orderIndex",
          "order": "ASCENDING"
        }
      ]
    },
    {
      "collectionGroup": "commerceProducts",
      "queryScope": "COLLECTION",
      "fields": [
        {
          "fieldPath": "visible",
          "order": "ASCENDING"
        },
        {
          "fieldPath": "subcategoryId",
          "order": "ASCENDING"
        },
        {
          "fieldPath": "orderIndex",
          "order": "ASCENDING"
        }
      ]
    }
  ],
  "fieldOverrides": []
}
